panel_vegafusion/__init__.py
panel_vegafusion/py.typed
panel_vegafusion/update.py
panel_vegafusion/utils.py
panel_vegafusion/vegafusion_pane.css
panel_vegafusion/vegafusion_pane.py
panel_vegafusion/vegafusion_pane_bokeh_ext.py
panel_vegafusion/assets/bundled/panel-vegafusion/692.js
panel_vegafusion/assets/bundled/panel-vegafusion/821.js
panel_vegafusion/assets/bundled/panel-vegafusion/882.js
panel_vegafusion/assets/bundled/panel-vegafusion/882.js.LICENSE.txt
panel_vegafusion/assets/bundled/panel-vegafusion/c689cfd619f9f777947a.module.wasm
panel_vegafusion/assets/bundled/panel-vegafusion/main.js
panel_vegafusion/models/__init__.py
panel_vegafusion/models/vegafusion_model.py
panel_vegafusion-0.0.3.dist-info/LICENSE
panel_vegafusion-0.0.3.dist-info/METADATA
panel_vegafusion-0.0.3.dist-info/WHEEL
panel_vegafusion-0.0.3.dist-info/top_level.txt
panel_vegafusion-0.0.3.dist-info/RECORD
