Metadata-Version: 2.1
Name: panel-vegafusion
Version: 0.0.3
Summary: Build interactive big data apps with Altair and Vega easily using Panel + VegaFusion.
Home-page: https://github.com/MarcSkovMadsen/panel-vegafusion
Author: Marc Skov Madsen
Author-email: marc.skov.madsen@gmailc.om
License: APGL3
Platform: UNKNOWN
Requires-Python: >=3.7
License-File: LICENSE
Requires-Dist: altair
Requires-Dist: panel
Requires-Dist: vegafusion-jupyter
Provides-Extra: all
Requires-Dist: autoflake ; extra == 'all'
Requires-Dist: black ; extra == 'all'
Requires-Dist: invoke ; extra == 'all'
Requires-Dist: ipywidgets-bokeh ; extra == 'all'
Requires-Dist: isort ; extra == 'all'
Requires-Dist: jupyter-bokeh ; extra == 'all'
Requires-Dist: jupyterlab ; extra == 'all'
Requires-Dist: mypy ; extra == 'all'
Requires-Dist: pylint ; extra == 'all'
Requires-Dist: pytest ; extra == 'all'
Requires-Dist: pytest-cov ; extra == 'all'
Requires-Dist: twine ; extra == 'all'
Requires-Dist: vega-datasets ; extra == 'all'
Requires-Dist: watchdog ; extra == 'all'
Provides-Extra: dev
Requires-Dist: autoflake ; extra == 'dev'
Requires-Dist: black ; extra == 'dev'
Requires-Dist: invoke ; extra == 'dev'
Requires-Dist: isort ; extra == 'dev'
Requires-Dist: mypy ; extra == 'dev'
Requires-Dist: pylint ; extra == 'dev'
Requires-Dist: pytest ; extra == 'dev'
Requires-Dist: pytest-cov ; extra == 'dev'
Requires-Dist: twine ; extra == 'dev'
Requires-Dist: watchdog ; extra == 'dev'
Provides-Extra: examples
Requires-Dist: ipywidgets-bokeh ; extra == 'examples'
Requires-Dist: jupyter-bokeh ; extra == 'examples'
Requires-Dist: jupyterlab ; extra == 'examples'
Requires-Dist: vega-datasets ; extra == 'examples'
